virtual_fields/__init__.py
virtual_fields/__init__.pyi
virtual_fields/_compat.py
virtual_fields/_util.py
virtual_fields/apps.py
virtual_fields/fields.py
virtual_fields/models.py
django_virtual_fields-0.0.2.dist-info/METADATA
django_virtual_fields-0.0.2.dist-info/WHEEL
django_virtual_fields-0.0.2.dist-info/RECORD
